energeasyapi/__init__.py
energeasyapi/api.py
energeasyapi/constants.py
energeasyapi/devices.py
energeasyapi/exceptions.py
energeasyapi/utils.py
energeasy_egguy-0.0.1.dist-info/LICENSE
energeasy_egguy-0.0.1.dist-info/METADATA
energeasy_egguy-0.0.1.dist-info/WHEEL
energeasy_egguy-0.0.1.dist-info/top_level.txt
energeasy_egguy-0.0.1.dist-info/RECORD
