Metadata-Version: 2.1
Name: energeasy-egguy
Version: 0.0.1
Summary: An API for the eanergeasy platform
Home-page: https://github.com/egguy/EnergEasyAPI
Author: Etienne "PoPs" G.
Author-email: crazypops@gmail.com
License: UNKNOWN
Platform: UNKNOWN
Classifier: Programming Language :: Python :: 3
Classifier: License :: OSI Approved :: MIT License
Classifier: Operating System :: OS Independent
Requires-Python: >=3.6
Requires-Dist: httpx (<0.17,>=0.16.0)
